README.txt
setup.py
Test/__init__.py
Test/binarySectorFile.py
Test/csvWriter.py
Test/fsid_data.py
Test/process_bm.py
Test/rawInputLogFile.py
process_bm.egg-info/PKG-INFO
process_bm.egg-info/SOURCES.txt
process_bm.egg-info/dependency_links.txt
process_bm.egg-info/not-zip-safe
process_bm.egg-info/top_level.txt