Metadata-Version: 1.0
Name: process-bm
Version: 0.7
Summary: my first python package
Home-page: https://github.com/sandeep-prabhu-git-hub/process_bm
Author: sandeep prabhu
Author-email: sandeep.kp@icloud.com
License: Edu License for learner
Platform: UNKNOWN
